cfei/smap/__init__.py
cfei/smap/cache.py
cfei/smap/select_response_schema.json
cfei/smap/subscribe_response_schema.json
cfei/smap/types.py
cfei/smap/validation.py
cfei/smap/tests/__init__.py
cfei/smap/tests/mockup.py
cfei/smap/tests/test_smap_freefunctions.py
cfei/smap/tests/test_smap_interface.py
cfei/smap/transport/__init__.py
cfei/smap/transport/aiohttp.py
cfei_smap-1.2.0.data/scripts/smap
cfei_smap-1.2.0.dist-info/METADATA
cfei_smap-1.2.0.dist-info/WHEEL
cfei_smap-1.2.0.dist-info/top_level.txt
cfei_smap-1.2.0.dist-info/RECORD
