Metadata-Version: 2.1
Name: cfei-smap
Version: 1.2.0
Summary: Interface to sMAP
Home-page: https://github.com/sdu-cfei/cfei-smap/
Author: Claudio Giovanni Mattera
Author-email: cgim@mmmi.sdu.dk
License: MIT
Platform: UNKNOWN
Requires-Dist: pandas
Requires-Dist: typing
Requires-Dist: aiohttp
Requires-Dist: appdirs
Requires-Dist: jsonschema
Requires-Dist: iso8601
